deepmux/__init__.py
deepmux/commands.py
deepmux/config.py
deepmux/exceptions.py
deepmux/interface.py
deepmux/model.py
deepmux/util.py
deepmux-0.4.1.dist-info/LICENSE
deepmux-0.4.1.dist-info/METADATA
deepmux-0.4.1.dist-info/WHEEL
deepmux-0.4.1.dist-info/top_level.txt
deepmux-0.4.1.dist-info/RECORD
